finder_sidebar_editor/FinderSidebarEditor.py
finder_sidebar_editor/__init__.py
finder_sidebar_editor/__main__.py
finder_sidebar_db-1.0.1.dist-info/LICENSE
finder_sidebar_db-1.0.1.dist-info/METADATA
finder_sidebar_db-1.0.1.dist-info/WHEEL
finder_sidebar_db-1.0.1.dist-info/entry_points.txt
finder_sidebar_db-1.0.1.dist-info/top_level.txt
finder_sidebar_db-1.0.1.dist-info/RECORD
