Metadata-Version: 2.1
Name: finder-sidebar-db
Version: 1.0.1
Summary: Module for editing the Favorites entries of the Finder sidebar.
Home-page: UNKNOWN
Author: db
Author-email: demetribair@gmail.com
Maintainer: DB
Maintainer-email: demetribair@gmail.com
License: MIT
Platform: UNKNOWN
Classifier: License :: OSI Approved :: MIT License
Classifier: Programming Language :: Python :: 3.7
Requires-Dist: pyobjc
